internetnl_domain_analyse/__init__.py
internetnl_domain_analyse/domain_analyse_classes.py
internetnl_domain_analyse/domain_plots.py
internetnl_domain_analyse/domein_analyse.py
internetnl_domain_analyse/latex_output.py
internetnl_domain_analyse/public_suffix_list.dat
internetnl_domain_analyse/utils.py
internetnl_domain_analyse-2.0.6.dist-info/AUTHORS.rst
internetnl_domain_analyse-2.0.6.dist-info/LICENSE.txt
internetnl_domain_analyse-2.0.6.dist-info/METADATA
internetnl_domain_analyse-2.0.6.dist-info/WHEEL
internetnl_domain_analyse-2.0.6.dist-info/entry_points.txt
internetnl_domain_analyse-2.0.6.dist-info/top_level.txt
internetnl_domain_analyse-2.0.6.dist-info/RECORD
