Metadata-Version: 2.1
Name: internetnl_domain_analyse
Version: 2.0.6
Summary: A tool to create image belong to internetnl time series
Home-page: https://github.com/eelcovv/internetnl_domain_analyse
Author: Eelco van Vliet
Author-email: 
License: MIT
Project-URL: Documentation, https://internetnl-domain-analyse.readthedocs.io/en/latest/
Platform: any
Classifier: Development Status :: 4 - Beta
Classifier: Programming Language :: Python
License-File: LICENSE.txt
License-File: AUTHORS.rst
Requires-Dist: weighted-sample-statistics
Requires-Dist: cbsplotlib
Requires-Dist: PyLaTeX
Requires-Dist: PyYAML
Requires-Dist: tldextract
Requires-Dist: tqdm
Requires-Dist: pandas
Requires-Dist: internetnl-scan
Requires-Dist: importlib-metadata
Requires-Dist: matplotlib
Requires-Dist: numpy
Requires-Dist: seaborn
Requires-Dist: requests
Requires-Dist: openpyxl
Requires-Dist: importlib-metadata; python_version < "3.8"
Provides-Extra: dev
Requires-Dist: pytest; extra == "dev"
Requires-Dist: pytest-cov; extra == "dev"
Requires-Dist: tox; extra == "dev"
Requires-Dist: pre-commit; extra == "dev"
Provides-Extra: testing
Requires-Dist: pytest; extra == "testing"
Requires-Dist: pytest-cov; extra == "testing"
